stwfsapy/__init__.py
stwfsapy/automata/__init__.py
stwfsapy/automata/construction.py
stwfsapy/automata/conversion.py
stwfsapy/automata/dfa.py
stwfsapy/automata/heap.py
stwfsapy/automata/nfa.py
stwfsapy/case_handlers.py
stwfsapy/expansion.py
stwfsapy/frequency_features.py
stwfsapy/position_features.py
stwfsapy/predictor.py
stwfsapy/tests/automata/__init__.py
stwfsapy/tests/automata/conftest.py
stwfsapy/tests/automata/construction_test.py
stwfsapy/tests/automata/conversion_test.py
stwfsapy/tests/automata/data.py
stwfsapy/tests/automata/dfa_test.py
stwfsapy/tests/automata/heap_test.py
stwfsapy/tests/automata/integration_test.py
stwfsapy/tests/automata/nfa_test.py
stwfsapy/tests/automata/search_overlap_regression_test.py
stwfsapy/tests/case_handlers_test.py
stwfsapy/tests/common.py
stwfsapy/tests/conftest.py
stwfsapy/tests/expansion/ampersand_expansion_test.py
stwfsapy/tests/expansion/any_case_from_braces_test.py
stwfsapy/tests/expansion/base_expansion_test.py
stwfsapy/tests/expansion/collect_test.py
stwfsapy/tests/expansion/common.py
stwfsapy/tests/expansion/expand_abbreviation_with_puntuation_test.py
stwfsapy/tests/expansion/simple_english_plural_test.py
stwfsapy/tests/expansion/upper_case_abbreviations_from_braces_test.py
stwfsapy/tests/frequency_features_test.py
stwfsapy/tests/position_features_test.py
stwfsapy/tests/predictor_test.py
stwfsapy/tests/text_features_test.py
stwfsapy/tests/thesaurus/__init__.py
stwfsapy/tests/thesaurus/common.py
stwfsapy/tests/thesaurus/conftest.py
stwfsapy/tests/thesaurus/extract_by_type_uri_test.py
stwfsapy/tests/thesaurus/extract_deprecated_test.py
stwfsapy/tests/thesaurus/extract_labels_test.py
stwfsapy/tests/thesaurus/extract_relation_by_uri_test.py
stwfsapy/tests/thesaurus/label_unwrapping_test.py
stwfsapy/tests/thesaurus/language_filter_test.py
stwfsapy/tests/thesaurus/retrieve_concept_labels_test.py
stwfsapy/tests/thesaurus/set_filter_test.py
stwfsapy/tests/thesaurus_features_test.py
stwfsapy/tests/upper_case_letters.py
stwfsapy-0.6.2.dist-info/METADATA
stwfsapy-0.6.2.dist-info/WHEEL
stwfsapy-0.6.2.dist-info/licenses/LICENSE
stwfsapy-0.6.2.dist-info/RECORD
