Metadata-Version: 2.4
Name: stwfsapy
Version: 0.6.2
Summary: A library for match labels of thesaurus concepts to text and assigning scores to found occurrences.
License: Apache-2.0
License-File: LICENSE
Author: AutoSE
Author-email: autose@zbw.eu
Requires-Python: >=3.10,<3.14
Classifier: Intended Audience :: Science/Research
Classifier: License :: OSI Approved :: Apache Software License
Classifier: Programming Language :: Python :: 3
Classifier: Programming Language :: Python :: 3.10
Classifier: Programming Language :: Python :: 3.11
Classifier: Programming Language :: Python :: 3.12
Classifier: Programming Language :: Python :: 3.13
Classifier: Topic :: Scientific/Engineering :: Artificial Intelligence
Requires-Dist: rdflib (>=7.1,<7.2)
Requires-Dist: scikit-learn (>0.24,<2.0)
Requires-Dist: scipy (>=1.15,<1.16)
Project-URL: Homepage, https://github.com/zbw/stwfsapy
